freezcord/Cog.py
freezcord/__init__.py
freezcord/bot.py
freezcord/guild.py
freezcord/load_cogs.py
freezcord/load_yaml.py
freezcord/webhook.py
freezcord-0.4.4.dist-info/METADATA
freezcord-0.4.4.dist-info/WHEEL
freezcord-0.4.4.dist-info/top_level.txt
freezcord-0.4.4.dist-info/RECORD
